archetypesdk/__init__.py
archetypesdk/api_request_thread.py
archetypesdk/api_requestor.py
archetypesdk/auth_requestor.py
archetypesdk/enums.py
archetypesdk/fastapi.py
archetypesdk/utils.py
archetypesdk/api_resources/__init__.py
archetypesdk/api_resources/api.py
archetypesdk/api_resources/api_resource.py
archetypesdk/api_resources/auth.py
archetypesdk/api_resources/billable_metric.py
archetypesdk/api_resources/client_ip.py
archetypesdk/api_resources/customer.py
archetypesdk/api_resources/endpoint.py
archetypesdk/api_resources/error.py
archetypesdk/api_resources/product.py
archetypesdk/api_resources/token.py
archetypesdk/api_resources/track.py
archetypesdk-1.0.16.dist-info/LICENSE
archetypesdk-1.0.16.dist-info/METADATA
archetypesdk-1.0.16.dist-info/WHEEL
archetypesdk-1.0.16.dist-info/top_level.txt
archetypesdk-1.0.16.dist-info/RECORD
