Metadata-Version: 2.1
Name: archetypesdk
Version: 1.0.16
Summary: Python bindings for Archetype. Archetype makes API monetization and usage based billing for APIs easy.
Home-page: https://github.com/ArchetypeAPI/
Author: Archetype
Author-email: hello@archetype.dev
Classifier: Programming Language :: Python :: 3
Classifier: Operating System :: OS Independent
Requires-Python: >=3.6
License-File: LICENSE
Requires-Dist: requests
Requires-Dist: Flask
